tor_project/__init__.py
tor_project-0.1.0.dist-info/WHEEL
tor_project-0.1.0.dist-info/METADATA
tor_project-0.1.0.dist-info/RECORD
