Metadata-Version: 2.1
Name: tor-project
Version: 0.1.0
Summary: 
Author: Ivan Yastrebov
Author-email: easy.-quest@mail.ru
Requires-Python: >=3.9,<4.0
Classifier: Programming Language :: Python :: 3
Classifier: Programming Language :: Python :: 3.9
Requires-Dist: Automat (>=20.2.0,<21.0.0)
Requires-Dist: Twisted (>=21.7.0,<22.0.0)
Requires-Dist: bs4 (>=0.0.1,<0.0.2)
Requires-Dist: cryptography (>=3.4.8,<4.0.0)
Requires-Dist: incremental (>=21.3.0,<22.0.0)
Requires-Dist: ipaddress (>=1.0.23,<2.0.0)
Requires-Dist: lxml (>=4.6.3,<5.0.0)
Requires-Dist: pygeoip (>=0.3.2,<0.4.0)
Requires-Dist: requests[socks] (>=2.26.0,<3.0.0)
Requires-Dist: txtorcon (>=21.1.0,<22.0.0)
Requires-Dist: zope.interface (>=5.4.0,<6.0.0)
